{"nodes": [{"id": "app_models_nexmo_number_rb", "label": "nexmo_number.rb", "file_type": "code", "source_file": "app/models/nexmo_number.rb", "source_location": "L1"}, {"id": "nexmo_number_nexmonumber", "label": "NexmoNumber", "file_type": "code", "source_file": "app/models/nexmo_number.rb", "source_location": "L1"}], "edges": [{"source": "app_models_nexmo_number_rb", "target": "nexmo_number_nexmonumber", "relation": "contains", "confidence": "EXTRACTED", "source_file": "app/models/nexmo_number.rb", "source_location": "L1", "weight": 1.0}]}